query_view/filter_sets.py
query_view/models.py
query_view/templates/query_view/query.html
query_view/templates/query_view/query.jinja
query_view/templatetags/__init__.py
query_view/templatetags/query_view_tags.py
query_view/views.py
django_query_view-0.1.6.dist-info/LICENSE
django_query_view-0.1.6.dist-info/METADATA
django_query_view-0.1.6.dist-info/WHEEL
django_query_view-0.1.6.dist-info/RECORD
