Metadata-Version: 2.1
Name: django-query-view
Version: 0.1.6
Summary: Django view for querying data
Home-page: https://github.com/enricobarzetti/django-query-view
License: MIT
Author: Enrico Barzetti
Author-email: enricobarzetti@gmail.com
Requires-Python: >=3.8,<4.0
Classifier: License :: OSI Approved :: MIT License
Classifier: Programming Language :: Python :: 3
Classifier: Programming Language :: Python :: 3.8
Classifier: Programming Language :: Python :: 3.9
Classifier: Programming Language :: Python :: 3.10
Classifier: Programming Language :: Python :: 3.11
Classifier: Programming Language :: Python :: 3.12
Requires-Dist: django-crispy-forms (>=1.10.0,<2.0.0)
Requires-Dist: django-extensions (>=3.1.0,<4.0.0)
Requires-Dist: django-filter (>=23.5,<24.0)
Requires-Dist: django-taggit (>=6.0.0,<7.0.0)
Requires-Dist: django_jinja (>=2.7.0,<3.0.0)
Requires-Dist: django_jinja_helpers (>=0.2.0,<0.3.0)
Requires-Dist: furl (>=2.1.0,<3.0.0)
Requires-Dist: taggit-selectize (>=2.10.0,<3.0.0)
